driverlib/__config__.py
driverlib/__init__.py
driverlib/types.py
driverlib/utils.py
driverlib/visa_driver.py
driverlib/agilent/__init__.py
driverlib/agilent/agilent_sa.py
driverlib/anapico/__init__.py
driverlib/anapico/anapico.py
driverlib/keithley/__init__.py
driverlib/keithley/keithley_dmm6500.py
driverlib/keysight/__init__.py
driverlib/keysight/keysight_na.py
driverlib/rhode_schwarz/__init__.py
driverlib/rhode_schwarz/rs_source.py
driverlib/rigol/__init__.py
driverlib/rigol/rigol_afg.py
driverlib/rigol/rigol_sa.py
driverlib/rigol/rigol_scope.py
driverlib/tektronix/__init__.py
driverlib/tektronix/tektronix_afg.py
driverlib/visa/__init__.py
driverlib/yokogawa/__init__.py
driverlib/yokogawa/yokogawa_7651.py
driverlib/yokogawa/yokogawa_gs200.py
driverlib-0.1.0.dist-info/LICENSE
driverlib-0.1.0.dist-info/METADATA
driverlib-0.1.0.dist-info/WHEEL
driverlib-0.1.0.dist-info/top_level.txt
driverlib-0.1.0.dist-info/RECORD
