Metadata-Version: 2.1
Name: driverlib
Version: 0.1.0
Summary: Control your instruments via USB or LAN.
Home-page: https://github.com/kyrylo-gr/driverlib
Author: kyrylo.gr | LKB-OMQ
Author-email: git@kyrylo.gr
Classifier: Programming Language :: Python :: 3
Classifier: Operating System :: OS Independent
Requires-Python: >=3.8
License-File: LICENSE
Requires-Dist: numpy
Requires-Dist: pyvisa
